pydantic_tools-0.3.3.dist-info/METADATA
pydantic_tools-0.3.3.dist-info/WHEEL
pydantic_tools/__init__.py
pydantic_tools/alias/__init__.py
pydantic_tools/i18n/__init__.py
pydantic_tools/i18n/__main__.py
pydantic_tools/i18n/locales/__init__.py
pydantic_tools/i18n/locales/zh_cn.py
pydantic_tools/i18n/model.py
pydantic_tools/i18n/templates.py
pydantic_tools/i18n/translate.py
pydantic_tools-0.3.3.dist-info/RECORD
