Metadata-Version: 2.1
Name: pydantic-tools
Version: 0.3.3
Summary: Useful tools for pydantic
Author-Email: icebear <iiiicebeaaaar@gmail.com>
License: MIT
Requires-Python: >=3.11
Requires-Dist: pydantic>=1.10.7
Requires-Dist: pytest>=7.3.1
Requires-Dist: rich>=13.3.5
Requires-Dist: bullet>=2.2.0
Requires-Dist: click>=8.1.3
